flatbuffers/__init__.py
flatbuffers/builder.py
flatbuffers/compat.py
flatbuffers/encode.py
flatbuffers/number_types.py
flatbuffers/packer.py
flatbuffers/table.py
physiq_flatbuffers-1.8.0.post8.dist-info/DESCRIPTION.rst
physiq_flatbuffers-1.8.0.post8.dist-info/METADATA
physiq_flatbuffers-1.8.0.post8.dist-info/RECORD
physiq_flatbuffers-1.8.0.post8.dist-info/WHEEL
physiq_flatbuffers-1.8.0.post8.dist-info/metadata.json
physiq_flatbuffers-1.8.0.post8.dist-info/top_level.txt
