Metadata-Version: 2.0
Name: physiq-flatbuffers
Version: 1.8.0-8
Summary: The FlatBuffers serialization format for Python
Home-page: https://github.com/google/flatbuffers
Author: FlatBuffers Contributors
Author-email: mike.holler@physiq.com
License: Apache 2.0
Platform: UNKNOWN
